baarutil/__init__.py
baarutil/baarlocker.py
baarutil/chromedriver_downloader.py
baarutil/converter.py
baarutil-1.9.4.1.dist-info/LICENSE
baarutil-1.9.4.1.dist-info/METADATA
baarutil-1.9.4.1.dist-info/WHEEL
baarutil-1.9.4.1.dist-info/top_level.txt
baarutil-1.9.4.1.dist-info/RECORD
