Metadata-Version: 2.1
Name: baarutil
Version: 1.9.4.1
Summary: Utility functions for BAAR developers
Home-page: https://github.com/Allied-Media/baarutil
Author: Souvik Roy
Author-email: souvik.roy@alliedmedia.com
License: UNKNOWN
Project-URL: Bug Tracker, https://github.com/Allied-Media/baarutil/issues
Platform: UNKNOWN
Classifier: Programming Language :: Python :: 3.7
Classifier: License :: OSI Approved :: MIT License
Classifier: Operating System :: OS Independent
Requires-Python: >=3.7
Requires-Dist: numpy (>=1.18.4)
Requires-Dist: pandas (>=1.0.3)
Requires-Dist: pycryptodome (>=3.9)
Requires-Dist: pybase64 (==1.2.0)
Requires-Dist: asn1crypto (==0.24.0)
Requires-Dist: robotframework-crypto (==0.3.0)
Requires-Dist: requests (>=2.28.1)
Requires-Dist: wget (>=3.2)
